gsgmorph/__init__.py
gsgmorph/matrix_form.py
gsgmorph/pyqubo_form.py
gsgmorph/utils.py
gsgmorph-1.0.2.dist-info/LICENSE
gsgmorph-1.0.2.dist-info/METADATA
gsgmorph-1.0.2.dist-info/WHEEL
gsgmorph-1.0.2.dist-info/top_level.txt
gsgmorph-1.0.2.dist-info/RECORD
