Metadata-Version: 2.1
Name: gsgmorph
Version: 1.0.2
Summary: The Graph/Subgraph Isomorphism Library for Quantum Annealers
Home-page: https://github.com/IffTech/GSG-Morph
Author: If and Only If (Iff) Technologies
Author-email: john@qcatdavis.org
License: UNKNOWN
Project-URL: Bug Tracker, https://github.com/IffTech/GSG-Morph/issues
Platform: UNKNOWN
Classifier: Programming Language :: Python :: 3
Classifier: License :: OSI Approved :: MIT License
Classifier: Operating System :: OS Independent
Classifier: Programming Language :: Python :: 3
Classifier: License :: OSI Approved :: GNU General Public License v3 (GPLv3)
Classifier: Operating System :: OS Independent
Classifier: Development Status :: 5 - Production/Stable
Classifier: Natural Language :: English
Classifier: Intended Audience :: Science/Research
Classifier: Intended Audience :: Education
Classifier: Topic :: Scientific/Engineering
Classifier: Topic :: Scientific/Engineering :: Mathematics
Classifier: Topic :: Scientific/Engineering :: Physics
Requires-Python: >=3.6
License-File: LICENSE
Requires-Dist: networkx
Requires-Dist: pyqubo
